flask_logger_decorator
