Metadata-Version: 1.1
Name: flask-logger-decorator
Version: 0.1.0
Summary: Flask logger decorator
Home-page: https://github.com/sunwei/flask-logger-decorator
Author: Sun Wei
Author-email: wayde.sun@gmail.com
License: UNKNOWN
Platform: UNKNOWN
Classifier: Development Status :: 4 - Beta
Classifier: Intended Audience :: Developers
Classifier: License :: OSI Approved :: MIT License
Classifier: Natural Language :: English
Classifier: Operating System :: OS Independent
Classifier: Programming Language :: Python
Classifier: Programming Language :: Python :: 3.4
Classifier: Programming Language :: Python :: 3.5
Classifier: Programming Language :: Python :: 3.6
Classifier: Topic :: Software Development :: Libraries :: Python Modules
